MANIFEST.in
README.md
setup.py
FunctionDesigner.egg-info/PKG-INFO
FunctionDesigner.egg-info/SOURCES.txt
FunctionDesigner.egg-info/dependency_links.txt
FunctionDesigner.egg-info/top_level.txt
functiondesigner/__init__.py
functiondesigner/functions.py
functiondesigner/operate.py
functiondesigner/setting.py