Metadata-Version: 1.1
Name: FunctionDesigner
Version: 1.0.0
Summary: to establish yourselfs function
Home-page: UNKNOWN
Author: zjy_090820
Author-email: a1234567890001919@outlook.com
License: UNKNOWN
Platform: UNKNOWN
Classifier: Programming Language :: Python :: 3
Classifier: License :: OSI Approved :: MIT License
Classifier: Operating System :: OS Independent
